pyaccl/__init__.py
pyaccl/accl.py
pyaccl-0.1.dist-info/LICENSE
pyaccl-0.1.dist-info/METADATA
pyaccl-0.1.dist-info/WHEEL
pyaccl-0.1.dist-info/top_level.txt
pyaccl-0.1.dist-info/RECORD
